imioweb.core-1.0a5-py3.10-nspkg.pth
imioweb/core/__init__.py
imioweb/core/configure.zcml
imioweb/core/interfaces.py
imioweb/core/permissions.zcml
imioweb/core/setuphandlers.py
imioweb/core/testing.py
imioweb/core/testing.zcml
imioweb/core/browser/__init__.py
imioweb/core/browser/configure.zcml
imioweb/core/browser/contact_info.py
imioweb/core/browser/view.py
imioweb/core/browser/overrides/.gitkeep
imioweb/core/browser/overrides/plone.app.contenttypes.browser.templates.listing_summary.pt
imioweb/core/browser/static/.gitkeep
imioweb/core/locales/README.rst
imioweb/core/locales/__init__.py
imioweb/core/locales/imioweb.core.pot
imioweb/core/locales/update.py
imioweb/core/locales/update.sh
imioweb/core/locales/en/LC_MESSAGES/imioweb.core.po
imioweb/core/profiles/default/actions.xml
imioweb/core/profiles/default/browserlayer.xml
imioweb/core/profiles/default/catalog.xml
imioweb/core/profiles/default/metadata.xml
imioweb/core/profiles/default/registry.xml
imioweb/core/profiles/default/rolemap.xml
imioweb/core/profiles/uninstall/browserlayer.xml
imioweb/core/tests/__init__.py
imioweb/core/tests/test_robot.py
imioweb/core/tests/test_setup.py
imioweb/core/tests/test_view.py
imioweb/core/tests/robot/test_example.robot
imioweb.core-1.0a5.dist-info/LICENSE.GPL
imioweb.core-1.0a5.dist-info/LICENSE.rst
imioweb.core-1.0a5.dist-info/METADATA
imioweb.core-1.0a5.dist-info/WHEEL
imioweb.core-1.0a5.dist-info/entry_points.txt
imioweb.core-1.0a5.dist-info/namespace_packages.txt
imioweb.core-1.0a5.dist-info/top_level.txt
imioweb.core-1.0a5.dist-info/RECORD
