Metadata-Version: 2.1
Name: imioweb.core
Version: 1.0a5
Summary: Core package for imioweb
Home-page: https://github.com/collective/imioweb.core
Author: Benoit Suttor
Author-email: benoit.suttor@imio.be
License: GPL version 2
Project-URL: PyPI, https://pypi.python.org/pypi/imioweb.core
Project-URL: Source, https://github.com/collective/imioweb.core
Project-URL: Tracker, https://github.com/collective/imioweb.core/issues
Keywords: Python Plone
Classifier: Environment :: Web Environment
Classifier: Framework :: Plone
Classifier: Framework :: Plone :: Addon
Classifier: Framework :: Plone :: 5.2
Classifier: Programming Language :: Python
Classifier: Programming Language :: Python :: 2.7
Classifier: Programming Language :: Python :: 3.6
Classifier: Programming Language :: Python :: 3.7
Classifier: Operating System :: OS Independent
Classifier: License :: OSI Approved :: GNU General Public License v2 (GPLv2)
Requires-Python: ==2.7, >=3.6
License-File: LICENSE.GPL
License-File: LICENSE.rst
Requires-Dist: setuptools
Requires-Dist: z3c.jbot
Requires-Dist: plone.api (>=1.8.4)
Requires-Dist: plone.restapi
Requires-Dist: plone.app.dexterity
Requires-Dist: collective.taxonomy
Provides-Extra: test
Requires-Dist: plone.app.testing ; extra == 'test'
Requires-Dist: plone.testing (>=5.0.0) ; extra == 'test'
Requires-Dist: plone.app.contenttypes ; extra == 'test'
Requires-Dist: plone.app.robotframework[debug] ; extra == 'test'
